[{
    "title": "Handlebars.js",
    "author": "Gabriel Manricks",
    "stock": 5,
    "price": 85,
    "cover": "img/bookHandlebars.jpg"
},

{
    "title": "Design Patterns",
    "author": "Gang of four",
    "stock": 12,
    "price": 75,
    "cover": "img/bookDesignpattern.jpg"
},

{
    "title": "Refactoring",
    "author": "Scott W.Ambler and Pramod J.Sadalage",
    "stock": 15,
    "price": 55,
    "cover": "img/bookRefactoring.jpg"
},

{
    "title": "Algorithms",
    "author": "Robert Sedgewich and Kevin Wayne",
    "stock": 21,
    "price": 25,
    "cover": "img/bookAlgorithms.jpg"
},

{
    "title": "Code complete 2",
    "author": "Steve McConell",
    "stock": 30,
    "price": 64,
    "cover": "img/bookCode2.jpg"
},

{
    "title": "Clean Code",
    "author": "Robert C.Martin",
    "stock": 33,
    "price": 54,
    "cover": "img/bookCleancode.jpg"
},

{
    "title": "Programation fundaments",
    "author": "Luis Joyanes Aguilar",
    "stock": 28,
    "price": 45,
    "cover": "img/bookFundamentos.jpg"
},

{
    "title": "Phyton",
    "author": "Alfredo Muños & Sheila Corcoles",
    "stock": 24,
    "price": 72,
    "cover": "img/python.jpg"
},
{
    "title": "Aprender React",
    "author": "Lionel Lopez",
    "stock": 14,
    "price": 55,
    "cover": "img/react.jpg"
},
{
    "title": "JS y Svelte",
    "author": "Justin Scherer",
    "stock": 4,
    "price": 19,
    "cover": "img/svelte.jpg"
},
{
    "title": "Programar con C++",
    "author": "Miguel Angel Acera",
    "stock": 13,
    "price": 23,
    "cover": "img/c++.jpg"
},
{
    "title": "JS y Svelte",
    "author": "Pepito Grillo",
    "stock": 22,
    "price": 45,
    "cover": "img/go.jpg"
}
]